Metadata-Version: 2.1
Name: files-gitpod
Version: 0.1.1
Summary: Meltano project files for gitpod
License-File: LICENSE
